{"url":"https://hubs.mozilla.com/scenes/CeJFEei","thumbnailFilename":"b6220e26-e7d2-4f2f-96f2-5da511c4699f.jpg","thumbnail":"https://uploads-prod.reticulum.io/files/b6220e26-e7d2-4f2f-96f2-5da511c4699f.jpg","title":"Message in a Bottle | Hubs by Mozilla","labels":[{"Name":"Soil","Confidence":99.99890899658203},{"Name":"Nature","Confidence":99.89714050292969},{"Name":"Sand","Confidence":99.85910034179688},{"Name":"Outdoors","Confidence":99.85910034179688},{"Name":"Dune","Confidence":97.32073211669922},{"Name":"Desert","Confidence":97.20673370361328}],"addedTime":"2022-10-24T05:21:19.816Z","updatedTime":"2022-10-29T10:12:11.271Z","hubEntityType":"scene","hubName":"Hubs by Mozilla","links":[],"version":4}