{"url":"https://hubs.mozilla.com/link/QBjmnYe","thumbnailFilename":"fd81c925-fd89-4bc7-a810-d3fb2f73b467.jpg","thumbnail":"https://uploads-prod.reticulum.io/files/fd81c925-fd89-4bc7-a810-d3fb2f73b467.jpg","title":"Seguridad Informática | Hubs by Mozilla","labels":[{"Name":"Building","Confidence":99.68814086914062},{"Name":"Architecture","Confidence":98.11180114746094},{"Name":"Window","Confidence":88.32518768310547},{"Name":"Hangar","Confidence":84.07807159423828},{"Name":"Skylight","Confidence":81.05418395996094},{"Name":"Flooring","Confidence":79.17668914794922}],"addedTime":"2022-10-31T06:25:41.508Z","updatedTime":"2022-10-31T06:25:46.636Z","hubEntityType":"room","hubName":"Hubs by Mozilla","links":[],"version":4}