{"url":"https://hubs.mozilla.com/UbTzCec/wads-garden","thumbnailFilename":"93d1be53-9359-4883-83e8-25611e0af22d.jpg","thumbnail":"https://uploads-prod.reticulum.io/files/93d1be53-9359-4883-83e8-25611e0af22d.jpg","title":"WADS (↑ ← → ↓) | Hubs by Mozilla","labels":[{"Name":"Flying","Confidence":99.01119995117188},{"Name":"Bird","Confidence":99.01119995117188},{"Name":"Animal","Confidence":99.01119995117188},{"Name":"Nature","Confidence":89.73548126220703},{"Name":"Airplane","Confidence":88.9747314453125},{"Name":"Transportation","Confidence":88.9747314453125},{"Name":"Vehicle","Confidence":88.9747314453125},{"Name":"Aircraft","Confidence":88.9747314453125},{"Name":"Outdoors","Confidence":87.59359741210938},{"Name":"Silhouette","Confidence":72.94113159179688}],"addedTime":"2022-10-29T11:03:17.130Z","updatedTime":"2022-10-29T11:03:20.358Z","hubEntityType":"room","hubName":"Hubs by Mozilla","links":[],"version":4}