{"url":"https://hubs.mozilla.com/scenes/Nmg7c7f","thumbnailFilename":"d4c4423f-b0d7-4892-8348-3527a932b1ef.jpg","thumbnail":"https://uploads-prod.reticulum.io/files/d4c4423f-b0d7-4892-8348-3527a932b1ef.jpg","title":"Test Scene | Hubs by Mozilla","labels":[{"Name":"Handrail","Confidence":99.9999771118164},{"Name":"Banister","Confidence":99.9999771118164},{"Name":"Railing","Confidence":99.67324829101562},{"Name":"Nature","Confidence":84.27141571044922},{"Name":"Outdoors","Confidence":83.89183044433594}]}