{"url":"https://hubs.mozilla.com/QqhQGUc/distant-touch","thumbnailFilename":"2ce627a4-fa60-4673-8c00-49bf43e9994a.jpg","thumbnail":"https://uploads-prod.reticulum.io/files/2ce627a4-fa60-4673-8c00-49bf43e9994a.jpg","title":"Distant Touch | Hubs by Mozilla","labels":[{"Name":"Chess","Confidence":98.21590423583984},{"Name":"Game","Confidence":98.21590423583984},{"Name":"Lighting","Confidence":90.96944427490234},{"Name":"Floor","Confidence":87.08496856689453},{"Name":"Flooring","Confidence":80.73795318603516},{"Name":"Indoors","Confidence":71.49171447753906},{"Name":"Room","Confidence":70.88895416259766}]}