{"url":"https://hubs.mozilla.com/link/AahZpjN","thumbnailFilename":"f6ba9c63-a3a9-4e39-8154-0ea6d639b670.jpg","thumbnail":"https://uploads-prod.reticulum.io/files/f6ba9c63-a3a9-4e39-8154-0ea6d639b670.jpg","title":"MakingXR Friday Mixer | Hubs by Mozilla","labels":[{"Name":"Lighting","Confidence":99.99300384521484},{"Name":"Building","Confidence":99.98066711425781},{"Name":"Architecture","Confidence":99.98066711425781},{"Name":"Club","Confidence":99.85107421875},{"Name":"Purple","Confidence":95.14100646972656},{"Name":"Disco","Confidence":92.10872650146484},{"Name":"Night Club","Confidence":92.10872650146484},{"Name":"Urban","Confidence":90.43449401855469},{"Name":"Indoors","Confidence":85.65435028076172},{"Name":"Interior Design","Confidence":79.92341613769531},{"Name":"Ballroom","Confidence":77.70648956298828},{"Name":"Room","Confidence":77.70648956298828}],"addedTime":"2022-11-26T10:54:15.781Z","updatedTime":"2022-11-26T10:54:20.127Z","hubEntityType":"room","hubName":"Hubs by Mozilla","links":[],"version":4}