{"url":"https://hubs.mozilla.com/scenes/9H6fvt8","thumbnailFilename":"2238cc88-f0e0-4e63-a1d9-0e9e346380df.jpg","thumbnail":"https://uploads-prod.reticulum.io/files/2238cc88-f0e0-4e63-a1d9-0e9e346380df.jpg","title":"Lu and Papago | Hubs by Mozilla","labels":[{"Name":"Wood","Confidence":89.46752166748047},{"Name":"Flagstone","Confidence":87.08793640136719},{"Name":"Soil","Confidence":86.9873275756836},{"Name":"Outdoors","Confidence":86.43437957763672},{"Name":"Brick","Confidence":84.55567932128906},{"Name":"Nature","Confidence":78.9332046508789}]}